[
  {
    "Symbol": "BTC",
    "close": 63546.29,
    "open": 63333.696,
    "high": 64153.072,
    "low": 62922.619,
    "volume": 9,
    "change": -12986.593,
    "sma5": 59264.9077999999,
    "sma20": 71365.9138000002,
    "sma50": 75501.2040200003,
    "vma5": 8.4,
    "vma20": 9.65,
    "vma50": 9.12,
    "score": 1,
    "yestscore": 1,
    "scorechange": 0,
    "perfsince": "NaN",
    "highsince": 0,
    "barssince": "NaN",
    "trailstop": -8622.8,
    "roc21": -25.3801206507736,
    "rsi2lessthan20": 0,
    "sharpe21": -0.0956945192851777,
    "closelessthanbbandlow": 0,
    "vspike": 0,
    "rank1": 50,
    "rank2": 100,
    "rank3": 100,
    "rank4": 0,
    "rank5": 100,
    "rank6": 100,
    "dpp": 75696.209,
    "weeklypp": 76018.121,
    "date": "06/19/2018",
    "fullname": "Bitcoin",
    "": ""
  },
  {
    "Symbol": "ETH",
    "close": 392689.89,
    "open": 378634.86,
    "high": 397585.34,
    "low": 376997.56,
    "volume": 731,
    "change": 24955.18,
    "sma5": 362330.419999999,
    "sma20": 430756.006499999,
    "sma50": 480916.5666,
    "vma5": 715,
    "vma20": 801.15,
    "vma50": 782.98,
    "score": 2,
    "yestscore": 3,
    "scorechange": 1,
    "perfsince": "NaN",
    "highsince": 0,
    "barssince": "NaN",
    "trailstop": 45255.53,
    "roc21": -40.4388337638572,
    "rsi2lessthan20": 0,
    "sharpe21": -0.0945678723514352,
    "closelessthanbbandlow": 0,
    "vspike": 0,
    "rank1": 100,
    "rank2": 0,
    "rank3": 50,
    "rank4": 50,
    "rank5": 50,
    "rank6": 50,
    "dpp": 363066.4,
    "weeklypp": 469763.136666668,
    "date": "06/19/2018",
    "fullname": "Ethereum",
    "": ""
  },
  {
    "Symbol": "LTC",
    "close": 357390.4,
    "open": 357293.8,
    "high": 365450.4,
    "low": 351653.2,
    "volume": 3616,
    "change": -66918.6,
    "sma5": 357866.580000001,
    "sma20": 422459.74,
    "sma50": 456865.923999999,
    "vma5": 3679.6,
    "vma20": 3954.55,
    "vma50": 3616.22,
    "score": 3,
    "yestscore": 2,
    "scorechange": -1,
    "perfsince": "NaN",
    "highsince": 0,
    "barssince": "NaN",
    "trailstop": -33813.15,
    "roc21": -26.066515030684,
    "rsi2lessthan20": 0,
    "sharpe21": -0.0870508967100811,
    "closelessthanbbandlow": 0,
    "vspike": 0,
    "rank1": 0,
    "rank2": 50,
    "rank3": 0,
    "rank4": 100,
    "rank5": 0,
    "rank6": 0,
    "dpp": 418117.1,
    "weeklypp": 475425.5,
    "date": "06/19/2018",
    "fullname": "LiteCoin",
    "": ""
  }
]